{
    "tus": [
        {
            "creation_method": "v4",
            "notes": [],
            "flags": "",
            "folio": "F.27.a",
            "tibetan": "༄༅༅། །འཕགས་པ་དཀོན་མཆོག་བརྩེགས་པ་ཆེན་པོའི་ཆོས་ཀྱི་རྣམ་གྲངས་ལེའུ་སྟོང་ཕྲག་བརྒྱ་པ་ལས་ལེའུ་སུམ་ཅུ་རྩ་བདུན་པ་སྟེ་འཕགས་པ་སེང་གེས་ཞུས་པ། ཤོ་ལོ་ཀ་དྲུག་ཅུ། རྒྱ་གར་སྐད་དུ། ཨཱརྱ་སིང་ཧ་པ་རི་པྲྀཙྪཱ་ནཱ་མ་མ་ཧཱ་ཡཱ་ན་སཱུ་ཏྲ། བོད་སྐད་དུ།",
            "english": "",
            "passage-xmlId": "UT22084-044-001",
            "creation_tool": "monlam-ai/84000",
            "volume": "44",
            "folio_xmlId": "UT4CZ5369-I1KG9170-0000/side/53"
        },
        {
            "creation_method": "v4",
            "notes": [],
            "flags": "",
            "folio": "F.27.a",
            "tibetan": "འཕགས་པ་སེང་གེས་ཞུས་པ་ཞེས་བྱ་བ་ཐེག་པ་ཆེན་པོའི་མདོ།",
            "english": "The Noble Great Vehicle Sūtra Siṃha’s Questions",
            "passage-xmlId": "UT22084-044-001",
            "creation_tool": "monlam-ai/84000",
            "volume": "44",
            "folio_xmlId": "UT4CZ5369-I1KG9170-0000/side/53"
        },
        {
            "creation_method": "v4",
            "notes": [],
            "flags": "",
            "folio": "F.27.a",
            "tibetan": "སངས་རྒྱས་དང་བྱང་ཆུབ་སེམས་དཔའ་ཐམས་ཅད་ལ་ཕྱག་འཚལ་ལོ།",
            "english": "Homage to all buddhas and bodhisattvas!",
            "passage-xmlId": "UT22084-044-001-26",
            "creation_tool": "monlam-ai/84000",
            "volume": "44",
            "folio_xmlId": "UT4CZ5369-I1KG9170-0000/side/53"
        },
        {
            "creation_method": "v4",
            "notes": [],
            "flags": "",
            "folio": "F.27.a",
            "tibetan": "།འདི་སྐད་བདག་གིས་ཐོས་པ་དུས་གཅིག་ན།",
            "english": "Thus did I hear at one time.",
            "passage-xmlId": "UT22084-044-001-26",
            "creation_tool": "monlam-ai/84000",
            "volume": "44",
            "folio_xmlId": "UT4CZ5369-I1KG9170-0000/side/53"
        },
        {
            "creation_method": "v4",
            "notes": [
                "UT22084-044-001-28"
            ],
            "flags": "",
            "folio": "F.27.a",
            "tibetan": "བཅོམ་ལྡན་འདས་རྒྱལ་པོའི་ཁབ་ན་བྱ་རྒོད་ཀྱི་ཕུང་པོའི་རི་ལ་དགེ་སློང་སྟོང་ཉིས་བརྒྱ་ལྔ་བཅུའི་དགེ་སློང་གི་དགེ་འདུན་ཆེན་པོ་དང་ཐབས་ཅིག་ཏུ་བཞུགས་ཏེ། བྱང་ཆུབ་སེམས་དཔའི་དགེ་འདུན་ཆེན་པོ་དང་ཡང་ཐབས་ཅིག་གོ།",
            "english": "The Blessed One was dwelling in Rājagṛha on Vulture Peak, together with a great saṅgha of 1,250 monks and a great saṅgha of bodhisattvas.",
            "passage-xmlId": "UT22084-044-001-26",
            "creation_tool": "monlam-ai/84000",
            "volume": "44",
            "folio_xmlId": "UT4CZ5369-I1KG9170-0000/side/53"
        },
        {
            "creation_method": "v4",
            "notes": [],
            "flags": "",
            "folio": "F.27.a",
            "tibetan": "།ཐམས་ཅད་མཁྱེན་ཅིང་ཐམས་ཅད་གཟིགས།",
            "english": "Knowing all and seeing all,",
            "passage-xmlId": "UT22084-044-001-29",
            "creation_tool": "monlam-ai/84000",
            "volume": "44",
            "folio_xmlId": "UT4CZ5369-I1KG9170-0000/side/53"
        },
        {
            "creation_method": "v4",
            "notes": [
                "UT22084-044-001-30"
            ],
            "flags": "",
            "folio": "F.27.a",
            "tibetan": "།རྒྱལ་བ་གང་ཟག་མཚུངས་པ་མེད།",
            "english": "The Victorious One is a peerless being.",
            "passage-xmlId": "UT22084-044-001-29",
            "creation_tool": "monlam-ai/84000",
            "volume": "44",
            "folio_xmlId": "UT4CZ5369-I1KG9170-0000/side/53"
        },
        {
            "creation_method": "v4",
            "notes": [
                "UT22084-044-001-31"
            ],
            "flags": "",
            "folio": "F.27.a",
            "tibetan": "།རྒྱལ་པོ་མ་སྐྱེས་དགྲ་ཡི་བུ།",
            "english": "The son of King Ajātaśatru",
            "passage-xmlId": "UT22084-044-001-29",
            "creation_tool": "monlam-ai/84000",
            "volume": "44",
            "folio_xmlId": "UT4CZ5369-I1KG9170-0000/side/53"
        },
        {
            "creation_method": "v4",
            "notes": [
                "UT22084-044-001-32",
                "UT22084-044-001-34"
            ],
            "flags": "",
            "folio": "F.27.a",
            "tibetan": "།སེང་གེ་ཞེས་ནི་གྲགས་པ་ཞིག །ཚོང་དཔོན་བུ་ཕོ་ལྔ་བརྒྱ་ཡིས། །མདུན་དུ་བདར་ཏེ་ལྷན་ཅིག་ཏུ།",
            "english": "Was known as Siṃha. {1} Accompanied and attended By five hundred wealthy noblemen,",
            "passage-xmlId": "UT22084-044-001-33",
            "creation_tool": "monlam-ai/84000",
            "volume": "44",
            "folio_xmlId": "UT4CZ5369-I1KG9170-0000/side/53"
        },
        {
            "creation_method": "v4",
            "notes": [],
            "flags": "",
            "folio": "F.27.a",
            "tibetan": "།རྒྱལ་པོའི་ཁབ་ནས་དེ་བྱུང་ནས།",
            "english": "He departed from Rājagṛha",
            "passage-xmlId": "UT22084-044-001-33",
            "creation_tool": "monlam-ai/84000",
            "volume": "44",
            "folio_xmlId": "UT4CZ5369-I1KG9170-0000/side/53"
        },
        {
            "creation_method": "v4",
            "notes": [
                "UT22084-044-001-35",
                "UT22084-044-001-37"
            ],
            "flags": "",
            "folio": "F.27.b",
            "tibetan": "།རྒྱལ་པོའི་འབྱོར་པ་ཆེན་པོ་ཡིས། །གསེར་ལས་བྱས་པའི་གདུགས་ཐོགས་ཏེ།",
            "english": "With great royal grandeur. {2} Carrying golden parasols,",
            "passage-xmlId": "UT22084-044-001-36",
            "creation_tool": "monlam-ai/84000",
            "volume": "44",
            "folio_xmlId": "UT4CZ5369-I1KG9170-0000/side/54"
        },
        {
            "creation_method": "v4",
            "notes": [],
            "flags": "",
            "folio": "F.27.b",
            "tibetan": "།རྫོགས་སངས་རྒྱས་ཀྱི་གན་སོང་ནས།",
            "english": "They went before the perfect Buddha.",
            "passage-xmlId": "UT22084-044-001-36",
            "creation_tool": "monlam-ai/84000",
            "volume": "44",
            "folio_xmlId": "UT4CZ5369-I1KG9170-0000/side/54"
        },
        {
            "creation_method": "v4",
            "notes": [],
            "flags": "",
            "folio": "F.27.b",
            "tibetan": "།ཞབས་ལ་མགོ་བོས་ཕྱག་འཚལ་ཏེ།",
            "english": "Bowing their heads to the feet of the Buddha,",
            "passage-xmlId": "UT22084-044-001-36",
            "creation_tool": "monlam-ai/84000",
            "volume": "44",
            "folio_xmlId": "UT4CZ5369-I1KG9170-0000/side/54"
        },
        {
            "creation_method": "v4",
            "notes": [],
            "flags": "",
            "folio": "F.27.b",
            "tibetan": "།ལྔ་བརྒྱ་པོ་ཡིས་གདུགས་དེ་དག །ཚང་བར་ཐུབ་པ་ཆེ་ལ་ཕུལ།",
            "english": "They offered the five hundred parasols. {3} Offering these to the Great Sage,",
            "passage-xmlId": "UT22084-044-001-38",
            "creation_tool": "monlam-ai/84000",
            "volume": "44",
            "folio_xmlId": "UT4CZ5369-I1KG9170-0000/side/54"
        },
        {
            "creation_method": "v4",
            "notes": [],
            "flags": "",
            "folio": "F.27.b",
            "tibetan": "།ཀུན་ཀྱང་བྱང་ཆུབ་དོན་དུ་ཞུགས།",
            "english": "All of them set out for awakening.",
            "passage-xmlId": "UT22084-044-001-38",
            "creation_tool": "monlam-ai/84000",
            "volume": "44",
            "folio_xmlId": "UT4CZ5369-I1KG9170-0000/side/54"
        },
        {
            "creation_method": "v4",
            "notes": [],
            "flags": "",
            "folio": "F.27.b",
            "tibetan": "།རྫོགས་སངས་རྒྱས་ཀྱི་མཐུ་ཡིས་ནི།",
            "english": "By the power of the perfect Buddha,",
            "passage-xmlId": "UT22084-044-001-38",
            "creation_tool": "monlam-ai/84000",
            "volume": "44",
            "folio_xmlId": "UT4CZ5369-I1KG9170-0000/side/54"
        },
        {
            "creation_method": "v4",
            "notes": [
                "UT22084-044-001-39"
            ],
            "flags": "",
            "folio": "F.27.b",
            "tibetan": "།དེ་དག་མི་འཇིགས་སྐྱེས་གྱུར་ནས།",
            "english": "They became fearless. {4}",
            "passage-xmlId": "UT22084-044-001-38",
            "creation_tool": "monlam-ai/84000",
            "volume": "44",
            "folio_xmlId": "UT4CZ5369-I1KG9170-0000/side/54"
        },
        {
            "creation_method": "v4",
            "notes": [],
            "flags": "",
            "folio": "F.27.b",
            "tibetan": "།སེང་གེས་ཐལ་མོ་སྦྱར་བྱས་ཏེ།",
            "english": "Siṃha joined his palms in reverence",
            "passage-xmlId": "UT22084-044-001-40",
            "creation_tool": "monlam-ai/84000",
            "volume": "44",
            "folio_xmlId": "UT4CZ5369-I1KG9170-0000/side/54"
        },
        {
            "creation_method": "v4",
            "notes": [
                "UT22084-044-001-41"
            ],
            "flags": "",
            "folio": "F.27.b",
            "tibetan": "།རྫོགས་སངས་རྒྱས་ལ་ཞུས་པ་ནི། །བྱང་ཆུབ་སེམས་དཔའི་སྤྱོད་པ་གང་། །དེ་ནི་འདྲེན་པས་བདག་ལ་གསུངས།",
            "english": "And asked the perfect Buddha, “Will the Guide please explain to me The conduct of bodhisattvas? {5}",
            "passage-xmlId": "UT22084-044-001-40",
            "creation_tool": "monlam-ai/84000",
            "volume": "44",
            "folio_xmlId": "UT4CZ5369-I1KG9170-0000/side/54"
        },
        {
            "creation_method": "v4",
            "notes": [],
            "flags": "",
            "folio": "F.27.b",
            "tibetan": "།གང་གིས་མཛེས་པར་འགྱུར་བ་ལགས།",
            "english": "“How does one become beautiful?",
            "passage-xmlId": "UT22084-044-001-42",
            "creation_tool": "monlam-ai/84000",
            "volume": "44",
            "folio_xmlId": "UT4CZ5369-I1KG9170-0000/side/54"
        },
        {
            "creation_method": "v4",
            "notes": [
                "UT22084-044-001-43"
            ],
            "flags": "",
            "folio": "F.27.b",
            "tibetan": "།གང་གིས་རྫུས་ཏེ་སྐྱེ་བར་འགྱུར།",
            "english": "How does one take miraculous birth?",
            "passage-xmlId": "UT22084-044-001-42",
            "creation_tool": "monlam-ai/84000",
            "volume": "44",
            "folio_xmlId": "UT4CZ5369-I1KG9170-0000/side/54"
        },
        {
            "creation_method": "v4",
            "notes": [],
            "flags": "",
            "folio": "F.27.b",
            "tibetan": "།སྐྱེ་བ་དྲན་པར་ཇི་ལྟར་འགྱུར།",
            "english": "How does one remember previous births?",
            "passage-xmlId": "UT22084-044-001-42",
            "creation_tool": "monlam-ai/84000",
            "volume": "44",
            "folio_xmlId": "UT4CZ5369-I1KG9170-0000/side/54"
        },
        {
            "creation_method": "v4",
            "notes": [],
            "flags": "",
            "folio": "F.27.b",
            "tibetan": "།ཐུབ་པ་ཆེན་པོས་ལུང་བསྟན་གསོལ།",
            "english": "Great Sage, please give your instruction.” {6}",
            "passage-xmlId": "UT22084-044-001-42",
            "creation_tool": "monlam-ai/84000",
            "volume": "44",
            "folio_xmlId": "UT4CZ5369-I1KG9170-0000/side/54"
        },
        {
            "creation_method": "v4",
            "notes": [],
            "flags": "",
            "folio": "F.27.b",
            "tibetan": "།དེ་དག་ལྷག་བསམ་ཡེ་ཤེས་ཀྱིས། །མཁྱེན་ནས་སངས་རྒྱས་ལུང་བསྟན་པ།",
            "english": "Knowing their pure intentions with his wisdom, The Buddha gave his instruction:",
            "passage-xmlId": "UT22084-044-001-44",
            "creation_tool": "monlam-ai/84000",
            "volume": "44",
            "folio_xmlId": "UT4CZ5369-I1KG9170-0000/side/54"
        },
        {
            "creation_method": "v4",
            "notes": [
                "UT22084-044-001-46"
            ],
            "flags": "",
            "folio": "F.27.b",
            "tibetan": "།བྱང་ཆུབ་སེམས་དཔའ་སྤྱོད་གང་ཞེས། །ཁྱོད་ཀྱི་དྲིས་པ་དེ་བསྟན་ཏོ།",
            "english": "“I will give a teaching on what you have asked: The conduct of bodhisattvas. {7}",
            "passage-xmlId": "UT22084-044-001-44",
            "creation_tool": "monlam-ai/84000",
            "volume": "44",
            "folio_xmlId": "UT4CZ5369-I1KG9170-0000/side/54"
        },
        {
            "creation_method": "v4",
            "notes": [],
            "flags": "",
            "folio": "F.27.b",
            "tibetan": "།བཟོད་པ་ཡིས་ནི་མཛེས་པར་འགྱུར།",
            "english": "“One becomes beautiful through patience.",
            "passage-xmlId": "UT22084-044-001-47",
            "creation_tool": "monlam-ai/84000",
            "volume": "44",
            "folio_xmlId": "UT4CZ5369-I1KG9170-0000/side/54"
        },
        {
            "creation_method": "v4",
            "notes": [
                "UT22084-044-001-48"
            ],
            "flags": "",
            "folio": "F.27.b",
            "tibetan": "།ཚངས་པར་སྤྱད་པས་རྫུས་ཏེ་སྐྱེ།",
            "english": "One takes miraculous birth by pure conduct.",
            "passage-xmlId": "UT22084-044-001-47",
            "creation_tool": "monlam-ai/84000",
            "volume": "44",
            "folio_xmlId": "UT4CZ5369-I1KG9170-0000/side/54"
        },
        {
            "creation_method": "v4",
            "notes": [],
            "flags": "",
            "folio": "F.27.b",
            "tibetan": "།ཆོས་ཀྱི་སྦྱིན་པས་སྐྱེ་བ་དྲན།",
            "english": "One recalls past lives by giving the Dharma.",
            "passage-xmlId": "UT22084-044-001-47",
            "creation_tool": "monlam-ai/84000",
            "volume": "44",
            "folio_xmlId": "UT4CZ5369-I1KG9170-0000/side/54"
        },
        {
            "creation_method": "v4",
            "notes": [
                "UT22084-044-001-49",
                "UT22084-044-001-51"
            ],
            "flags": "",
            "folio": "F.27.b",
            "tibetan": "།གཞོན་ནུ་དེ་ལྟར་ཤེས་པར་གྱིས། །གང་གིས་སུམ་ཅུ་རྩ་གཉིས་མཚན། །དཔེ་བྱད་བཟང་པོ་བརྒྱད་ཅུ་དང་། །གསེར་མདོག་འདྲ་བའི་ལུས་འགྱུར་ཞིང་། །དེ་མཐོང་སེམས་ཅན་དགའ་བར་འགྱུར།",
            "english": "Youth, know it to be thus!” {8} “How does one manifest The thirty-two marks, the eighty excellent signs, And a body radiant like gold That delights beings upon seeing?” {9}",
            "passage-xmlId": "UT22084-044-001-50",
            "creation_tool": "monlam-ai/84000",
            "volume": "44",
            "folio_xmlId": "UT4CZ5369-I1KG9170-0000/side/54"
        },
        {
            "creation_method": "v4",
            "notes": [],
            "flags": "",
            "folio": "F.27.b",
            "tibetan": "།སྦྱིན་པ་ཀུན་གྱིས་མཚན་དུ་འགྱུར།",
            "english": "“The marks manifest through complete generosity.",
            "passage-xmlId": "UT22084-044-001-52",
            "creation_tool": "monlam-ai/84000",
            "volume": "44",
            "folio_xmlId": "UT4CZ5369-I1KG9170-0000/side/54"
        },
        {
            "creation_method": "v4",
            "notes": [],
            "flags": "",
            "folio": "F.27.b",
            "tibetan": "།བྱམས་པས་དེ་བཞིན་དཔེ་བྱད་བཟང་།",
            "english": "Likewise, the excellent signs come to be through love.",
            "passage-xmlId": "UT22084-044-001-52",
            "creation_tool": "monlam-ai/84000",
            "volume": "44",
            "folio_xmlId": "UT4CZ5369-I1KG9170-0000/side/54"
        },
        {
            "creation_method": "v4",
            "notes": [
                "UT22084-044-001-53"
            ],
            "flags": "",
            "folio": "F.27.b",
            "tibetan": "།སེམས་ཅན་ཀུན་ལ་སེམས་མཉམ་པས། །རྒྱལ་བ་གསེར་གྱི་མདོག་འདྲར་འགྱུར།",
            "english": "The golden radiance of the victorious ones Manifests by having an attitude of equality toward all beings.” {10}",
            "passage-xmlId": "UT22084-044-001-52",
            "creation_tool": "monlam-ai/84000",
            "volume": "44",
            "folio_xmlId": "UT4CZ5369-I1KG9170-0000/side/54"
        },
        {
            "creation_method": "v4",
            "notes": [],
            "flags": "",
            "folio": "F.27.b",
            "tibetan": "།གཟུངས་ནི་གང་གིས་ཐོབ་པར་འགྱུར།",
            "english": "“How is retention attained?",
            "passage-xmlId": "UT22084-044-001-54",
            "creation_tool": "monlam-ai/84000",
            "volume": "44",
            "folio_xmlId": "UT4CZ5369-I1KG9170-0000/side/54"
        },
        {
            "creation_method": "v4",
            "notes": [],
            "flags": "",
            "folio": "F.27.b",
            "tibetan": "།གང་གིས་ཏིང་འཛིན་སྐྱེ་འགྱུར་ལགས།",
            "english": "How does absorption arise?",
            "passage-xmlId": "UT22084-044-001-54",
            "creation_tool": "monlam-ai/84000",
            "volume": "44",
            "folio_xmlId": "UT4CZ5369-I1KG9170-0000/side/54"
        },
        {
            "creation_method": "v4",
            "notes": [],
            "flags": "",
            "folio": "F.27.b",
            "tibetan": "།གཟུང་བའི་ཚིག་ཏུ་གང་གིས་འགྱུར།",
            "english": "How do statements become acceptable?",
            "passage-xmlId": "UT22084-044-001-54",
            "creation_tool": "monlam-ai/84000",
            "volume": "44",
            "folio_xmlId": "UT4CZ5369-I1KG9170-0000/side/54"
        },
        {
            "creation_method": "v4",
            "notes": [
                "UT22084-044-001-55"
            ],
            "flags": "",
            "folio": "F.27.b",
            "tibetan": "།ཐུབ་པ་ཆེན་པོས་ལུང་བསྟན་གསོལ།",
            "english": "Great Sage, please give your teaching!” {11}",
            "passage-xmlId": "UT22084-044-001-54",
            "creation_tool": "monlam-ai/84000",
            "volume": "44",
            "folio_xmlId": "UT4CZ5369-I1KG9170-0000/side/54"
        },
        {
            "creation_method": "v4",
            "notes": [],
            "flags": "",
            "folio": "F.27.b",
            "tibetan": "།ཆོས་ལ་བཟོད་པས་གཟུངས་རྣམས་འཐོབ།",
            "english": "“Retention is attained through receptivity to the Dharma.",
            "passage-xmlId": "UT22084-044-001-56",
            "creation_tool": "monlam-ai/84000",
            "volume": "44",
            "folio_xmlId": "UT4CZ5369-I1KG9170-0000/side/54"
        },
        {
            "creation_method": "v4",
            "notes": [
                "UT22084-044-001-57"
            ],
            "flags": "",
            "folio": "F.27.b",
            "tibetan": "།སེམས་བསྒོམས་པས་ནི་ཏིང་འཛིན་སྐྱེ། །ཀྱལ་བའི་ཚིག་རྣམས་སྤང་བྱས་ན། །གཟུང་བར་འོས་པའི་ཚིག་ཏུ་འགྱུར།",
            "english": "Absorption arises by training the mind. Statements become acceptable When one abandons senseless talk.” {12}",
            "passage-xmlId": "UT22084-044-001-56",
            "creation_tool": "monlam-ai/84000",
            "volume": "44",
            "folio_xmlId": "UT4CZ5369-I1KG9170-0000/side/54"
        },
        {
            "creation_method": "v4",
            "notes": [],
            "flags": "",
            "folio": "F.27.b",
            "tibetan": "།དྲན་དང་ལྡན་པར་ཇི་ལྟར་འགྱུར།",
            "english": "“How does one become mindful?",
            "passage-xmlId": "UT22084-044-001-58",
            "creation_tool": "monlam-ai/84000",
            "volume": "44",
            "folio_xmlId": "UT4CZ5369-I1KG9170-0000/side/54"
        },
        {
            "creation_method": "v4",
            "notes": [
                "UT22084-044-001-59"
            ],
            "flags": "",
            "folio": "F.27.b",
            "tibetan": "།ཐུབ་པ་ཇི་ལྟར་བློ་གྲོས་ལྡན།",
            "english": "O Sage, how does one become intelligent?",
            "passage-xmlId": "UT22084-044-001-58",
            "creation_tool": "monlam-ai/84000",
            "volume": "44",
            "folio_xmlId": "UT4CZ5369-I1KG9170-0000/side/54"
        },
        {
            "creation_method": "v4",
            "notes": [
                "UT22084-044-001-60"
            ],
            "flags": "",
            "folio": "F.27.b",
            "tibetan": "།ཇི་ལྟར་ཆོས་སྤྱོད་འགྱུར་བ་ལགས།",
            "english": "How does one come to act according to the Dharma?",
            "passage-xmlId": "UT22084-044-001-58",
            "creation_tool": "monlam-ai/84000",
            "volume": "44",
            "folio_xmlId": "UT4CZ5369-I1KG9170-0000/side/54"
        },
        {
            "creation_method": "v4",
            "notes": [
                "UT22084-044-001-61",
                "UT22084-044-001-62"
            ],
            "flags": "",
            "folio": "F.27.b",
            "tibetan": "།སྐྱེས་བུ་དམ་པ་མཁས་ཅིས་འགྱུར།",
            "english": "O Holy Being, how does one become wise?” {13}",
            "passage-xmlId": "UT22084-044-001-58",
            "creation_tool": "monlam-ai/84000",
            "volume": "44",
            "folio_xmlId": "UT4CZ5369-I1KG9170-0000/side/54"
        },
        {
            "creation_method": "v4",
            "notes": [
                "UT22084-044-001-64"
            ],
            "flags": "",
            "folio": "F.28.a",
            "tibetan": "།གཡོ་མེད་པས་ནི་དྲན་ལྡན་འགྱུར།",
            "english": "“One comes to possess mindfulness by being undeceiving.",
            "passage-xmlId": "UT22084-044-001-63",
            "creation_tool": "monlam-ai/84000",
            "volume": "44",
            "folio_xmlId": "UT4CZ5369-I1KG9170-0000/side/55"
        },
        {
            "creation_method": "v4",
            "notes": [],
            "flags": "",
            "folio": "F.28.a",
            "tibetan": "།དོན་ལ་སེམས་པས་བློ་གྲོས་ལྡན།",
            "english": "One becomes intelligent by contemplating meaning.",
            "passage-xmlId": "UT22084-044-001-63",
            "creation_tool": "monlam-ai/84000",
            "volume": "44",
            "folio_xmlId": "UT4CZ5369-I1KG9170-0000/side/55"
        },
        {
            "creation_method": "v4",
            "notes": [
                "UT22084-044-001-65"
            ],
            "flags": "",
            "folio": "F.28.a",
            "tibetan": "།གུས་དང་བཅས་པས་ཆོས་སྤྱོད་འགྱུར།",
            "english": "One comes to act according to the Dharma by having reverence.",
            "passage-xmlId": "UT22084-044-001-63",
            "creation_tool": "monlam-ai/84000",
            "volume": "44",
            "folio_xmlId": "UT4CZ5369-I1KG9170-0000/side/55"
        },
        {
            "creation_method": "v4",
            "notes": [
                "UT22084-044-001-66"
            ],
            "flags": "",
            "folio": "F.28.a",
            "tibetan": "།ཆོས་ཀྱི་མཚན་ཉིད་རྟོགས་པས་མཁས། །",
            "english": "One becomes wise by knowing the characteristics of phenomena.” {14}",
            "passage-xmlId": "UT22084-044-001-63",
            "creation_tool": "monlam-ai/84000",
            "volume": "44",
            "folio_xmlId": "UT4CZ5369-I1KG9170-0000/side/55"
        },
        {
            "creation_method": "v4",
            "notes": [
                "UT22084-044-001-68",
                "UT22084-044-001-69"
            ],
            "flags": "",
            "folio": "F.28.a",
            "tibetan": "འཇིག་རྟེན་མགོན་པོའི་སྤྱན་སྔར་ནི། །ལས་གང་གིས་ནི་སྐྱེ་བར་འགྱུར།",
            "english": "“By what action is a bodhisattva born In the presence of the guardians of the world?",
            "passage-xmlId": "UT22084-044-001-67",
            "creation_tool": "monlam-ai/84000",
            "volume": "44",
            "folio_xmlId": "UT4CZ5369-I1KG9170-0000/side/55"
        },
        {
            "creation_method": "v4",
            "notes": [
                "UT22084-044-001-70",
                "UT22084-044-001-71"
            ],
            "flags": "",
            "folio": "F.28.a",
            "tibetan": "།འཇིག་རྟེན་མགོན་གྱི་མངོན་སུམ་དུ། །ཞུ་བ་ཞུ་བར་ཇི་ལྟར་འགྱུར།",
            "english": "How do they come to ask questions Directly before the guardians of the world?” {15}",
            "passage-xmlId": "UT22084-044-001-67",
            "creation_tool": "monlam-ai/84000",
            "volume": "44",
            "folio_xmlId": "UT4CZ5369-I1KG9170-0000/side/55"
        },
        {
            "creation_method": "v4",
            "notes": [
                "UT22084-044-001-73",
                "UT22084-044-001-74"
            ],
            "flags": "",
            "folio": "F.28.a",
            "tibetan": "།གང་ཞིག་ཆོས་ཀྱི་སྦྱིན་པ་ལ། །ནམ་ཡང་བར་ཆད་མི་བྱེད་པ། །དེ་ནི་དེས་ན་མྱུར་རབ་ཏུ། །འཇིག་རྟེན་མགོན་དང་ཕྲད་པར་འགྱུར།",
            "english": "“The one who never obstructs The giving of Dharma Will with great swiftness Come to meet the guardians of the world.” {16}",
            "passage-xmlId": "UT22084-044-001-72",
            "creation_tool": "monlam-ai/84000",
            "volume": "44",
            "folio_xmlId": "UT4CZ5369-I1KG9170-0000/side/55"
        },
        {
            "creation_method": "v4",
            "notes": [],
            "flags": "",
            "folio": "F.28.a",
            "tibetan": "།གང་གིས་མི་ཁོམ་སྤོང་བར་འགྱུར།",
            "english": "“How does one relinquish rebirth in inopportune states?",
            "passage-xmlId": "UT22084-044-001-75",
            "creation_tool": "monlam-ai/84000",
            "volume": "44",
            "folio_xmlId": "UT4CZ5369-I1KG9170-0000/side/55"
        },
        {
            "creation_method": "v4",
            "notes": [],
            "flags": "",
            "folio": "F.28.a",
            "tibetan": "།གང་གིས་བཟང་འགྲོར་མཆི་འགྱུར་ལགས། །སྐྱེ་བ་ཀུན་ཏུ་སྐྱེ་བ་ན། །བག་མཆིས་པར་ནི་ཇི་ལྟར་འགྱུར།",
            "english": "How does one go forth to favorable states? How does one become heedful Wherever one takes birth throughout all of one’s lives?” {17}",
            "passage-xmlId": "UT22084-044-001-75",
            "creation_tool": "monlam-ai/84000",
            "volume": "44",
            "folio_xmlId": "UT4CZ5369-I1KG9170-0000/side/55"
        },
        {
            "creation_method": "v4",
            "notes": [
                "UT22084-044-001-77"
            ],
            "flags": "",
            "folio": "F.28.a",
            "tibetan": "།དད་པས་མི་ཁོམ་སྤོང་བར་འགྱུར།",
            "english": "“Inopportune births are relinquished through faith.",
            "passage-xmlId": "UT22084-044-001-76",
            "creation_tool": "monlam-ai/84000",
            "volume": "44",
            "folio_xmlId": "UT4CZ5369-I1KG9170-0000/side/55"
        },
        {
            "creation_method": "v4",
            "notes": [
                "UT22084-044-001-78"
            ],
            "flags": "",
            "folio": "F.28.a",
            "tibetan": "།ཚུལ་ཁྲིམས་ཀྱིས་ནི་བཟང་འགྲོར་འགྲོ། །སྟོང་པ་ཉིད་ནི་བསྒོམ་བྱས་ན། །རྟག་ཏུ་བག་དང་ལྡན་པར་འགྱུར།",
            "english": "One goes forth to favorable states through moral discipline. One becomes always heedful By becoming familiar with emptiness.” {18}",
            "passage-xmlId": "UT22084-044-001-76",
            "creation_tool": "monlam-ai/84000",
            "volume": "44",
            "folio_xmlId": "UT4CZ5369-I1KG9170-0000/side/55"
        },
        {
            "creation_method": "v4",
            "notes": [
                "UT22084-044-001-80",
                "UT22084-044-001-81"
            ],
            "flags": "",
            "folio": "F.28.a",
            "tibetan": "།ཐུབ་པ་བྱང་ཆུབ་སེམས་དཔའ་རྣམས། །ཇི་ལྟར་ལས་རྣམས་དག་པར་འགྱུར།",
            "english": "“O Sage, how do bodhisattvas Purify their karma?",
            "passage-xmlId": "UT22084-044-001-79",
            "creation_tool": "monlam-ai/84000",
            "volume": "44",
            "folio_xmlId": "UT4CZ5369-I1KG9170-0000/side/55"
        },
        {
            "creation_method": "v4",
            "notes": [],
            "flags": "",
            "folio": "F.28.a",
            "tibetan": "།ཇི་ལྟར་བདུད་ཀྱི་སྙིས་མི་ཐོགས།",
            "english": "How do they dodge the snares of Māra?",
            "passage-xmlId": "UT22084-044-001-79",
            "creation_tool": "monlam-ai/84000",
            "volume": "44",
            "folio_xmlId": "UT4CZ5369-I1KG9170-0000/side/55"
        },
        {
            "creation_method": "v4",
            "notes": [
                "UT22084-044-001-82"
            ],
            "flags": "",
            "folio": "F.28.a",
            "tibetan": "།ཇི་ལྟར་ཆོས་ཀྱིས་ཕོངས་འགྱུར་སྤོང་། །",
            "english": "How do they avoid becoming bereft of Dharma?” {19}",
            "passage-xmlId": "UT22084-044-001-79",
            "creation_tool": "monlam-ai/84000",
            "volume": "44",
            "folio_xmlId": "UT4CZ5369-I1KG9170-0000/side/55"
        },
        {
            "creation_method": "v4",
            "notes": [
                "UT22084-044-001-84",
                "UT22084-044-001-85"
            ],
            "flags": "",
            "folio": "F.28.a",
            "tibetan": "རྣམ་པར་གྲོལ་བས་ལས་རྣམས་འདག །བརྩོན་འགྲུས་ཀྱིས་ནི་བདུད་འདུལ་འགྱུར། །ཅི་སྨྲས་དེ་བཞིན་བྱེད་པས་ནི། །ཆོས་ཀྱིས་ཕོངས་པ་སྤོང་བར་འགྱུར།",
            "english": "“Karma is purified through firm resolution. Māra is subdued through perseverance. They avoid becoming bereft of the Dharma By acting according to their words.” {20}",
            "passage-xmlId": "UT22084-044-001-83",
            "creation_tool": "monlam-ai/84000",
            "volume": "44",
            "folio_xmlId": "UT4CZ5369-I1KG9170-0000/side/55"
        },
        {
            "creation_method": "v4",
            "notes": [
                "UT22084-044-001-87",
                "UT22084-044-001-88"
            ],
            "flags": "",
            "folio": "F.28.a",
            "tibetan": "།ཀ་ལ་པིང་ཀའི་སྒྲ་སྙན་དང་། །ཚངས་པའི་དབྱངས་འདྲར་ཇི་ལྟར་འགྱུར། །ཐུབ་པ་མོས་པ་སྣ་ཚོགས་ཀྱི། །སེམས་ཅན་རྣམས་ནི་གང་གིས་དགའ།",
            "english": "“How does one’s voice become like the pleasing song Of the kalaviṅka bird and like the voice of Brahmā? O Sage, how does one please beings With their diverse inclinations?” {21}",
            "passage-xmlId": "UT22084-044-001-86",
            "creation_tool": "monlam-ai/84000",
            "volume": "44",
            "folio_xmlId": "UT4CZ5369-I1KG9170-0000/side/55"
        },
        {
            "creation_method": "v4",
            "notes": [],
            "flags": "",
            "folio": "F.28.a",
            "tibetan": "།བདེན་པར་སྨྲས་པས་ཚངས་པའི་དབྱངས།",
            "english": "“The voice of Brahmā is obtained by speaking truthfully.",
            "passage-xmlId": "UT22084-044-001-89",
            "creation_tool": "monlam-ai/84000",
            "volume": "44",
            "folio_xmlId": "UT4CZ5369-I1KG9170-0000/side/55"
        },
        {
            "creation_method": "v4",
            "notes": [
                "UT22084-044-001-90",
                "UT22084-044-001-91",
                "UT22084-044-001-92"
            ],
            "flags": "",
            "folio": "F.28.a",
            "tibetan": "།ངག་རྩུབ་སྤངས་པས་སྒྲ་སྙན་འགྱུར། །ཀྱལ་བའི་ཚིག་དང་ཕྲ་མ་རྣམས། །སྤངས་པས་སེམས་ཅན་དགའ་བར་འགྱུར།",
            "english": "The voice becomes pleasing by abandoning harsh words. One pleases beings By relinquishing senseless talk and slander.” {22}",
            "passage-xmlId": "UT22084-044-001-89",
            "creation_tool": "monlam-ai/84000",
            "volume": "44",
            "folio_xmlId": "UT4CZ5369-I1KG9170-0000/side/55"
        },
        {
            "creation_method": "v4",
            "notes": [],
            "flags": "",
            "folio": "F.28.a",
            "tibetan": "།ཇི་ལྟར་ཚེ་རིང་འགྱུར་བ་ལགས།",
            "english": "“How does one come to have a long life?",
            "passage-xmlId": "UT22084-044-001-93",
            "creation_tool": "monlam-ai/84000",
            "volume": "44",
            "folio_xmlId": "UT4CZ5369-I1KG9170-0000/side/55"
        },
        {
            "creation_method": "v4",
            "notes": [],
            "flags": "",
            "folio": "F.28.a",
            "tibetan": "།བྲོ་ནད་ཉུང་བར་ཇི་ལྟར་འགྱུར།",
            "english": "How does one come to have fewer illnesses?",
            "passage-xmlId": "UT22084-044-001-93",
            "creation_tool": "monlam-ai/84000",
            "volume": "44",
            "folio_xmlId": "UT4CZ5369-I1KG9170-0000/side/55"
        },
        {
            "creation_method": "v4",
            "notes": [
                "UT22084-044-001-94"
            ],
            "flags": "",
            "folio": "F.28.a",
            "tibetan": "།རྣམ་པར་འདྲེན་པ་གང་གིས་ན།",
            "english": "How, O Supreme Guide,",
            "passage-xmlId": "UT22084-044-001-93",
            "creation_tool": "monlam-ai/84000",
            "volume": "44",
            "folio_xmlId": "UT4CZ5369-I1KG9170-0000/side/55"
        },
        {
            "creation_method": "v4",
            "notes": [
                "UT22084-044-001-95"
            ],
            "flags": "",
            "folio": "F.28.a",
            "tibetan": "།གཡོག་འཁོར་རྣམས་ནི་མི་ཕྱེད་འགྱུར།",
            "english": "Does a retinue come to be undivided?” {23}",
            "passage-xmlId": "UT22084-044-001-93",
            "creation_tool": "monlam-ai/84000",
            "volume": "44",
            "folio_xmlId": "UT4CZ5369-I1KG9170-0000/side/55"
        },
        {
            "creation_method": "v4",
            "notes": [],
            "flags": "",
            "folio": "F.28.a",
            "tibetan": "།གསོད་པ་མི་བྱེད་ཚེ་རིང་འགྱུར།",
            "english": "“One comes to have a long life by not killing.",
            "passage-xmlId": "UT22084-044-001-96",
            "creation_tool": "monlam-ai/84000",
            "volume": "44",
            "folio_xmlId": "UT4CZ5369-I1KG9170-0000/side/55"
        },
        {
            "creation_method": "v4",
            "notes": [
                "UT22084-044-001-97"
            ],
            "flags": "",
            "folio": "F.28.a",
            "tibetan": "།མི་འཚེ་བས་ནི་ནད་ཉུང་འགྱུར། །མི་འཐུན་པ་དག་བསྡུམས་བྱས་ན། །གཡོག་འཁོར་རྣམས་ནི་མི་ཕྱེད་འགྱུར།",
            "english": "One will have fewer illnesses by causing no harm. A retinue comes to be undivided When one reconciles disputes.” {24}",
            "passage-xmlId": "UT22084-044-001-96",
            "creation_tool": "monlam-ai/84000",
            "volume": "44",
            "folio_xmlId": "UT4CZ5369-I1KG9170-0000/side/55"
        },
        {
            "creation_method": "v4",
            "notes": [
                "UT22084-044-001-99"
            ],
            "flags": "",
            "folio": "F.28.a",
            "tibetan": "།དོན་རྣམས་ཇི་ལྟར་འགྲུབ་འགྱུར་ལགས།",
            "english": "“How does one obtain wealth?",
            "passage-xmlId": "UT22084-044-001-98",
            "creation_tool": "monlam-ai/84000",
            "volume": "44",
            "folio_xmlId": "UT4CZ5369-I1KG9170-0000/side/55"
        },
        {
            "creation_method": "v4",
            "notes": [],
            "flags": "",
            "folio": "F.28.a",
            "tibetan": "།གང་གིས་ལོངས་སྤྱོད་མི་ཉམས་འགྱུར། གང་དང་གང་དུ་སྐྱེ་བ་དེར། །དབང་ཆེན་གྲགས་པར་ཇི་ལྟར་འགྱུར།",
            "english": "How do possessions cease to diminish? How does one become distinguished Wherever one is born?” {25}",
            "passage-xmlId": "UT22084-044-001-98",
            "creation_tool": "monlam-ai/84000",
            "volume": "44",
            "folio_xmlId": "UT4CZ5369-I1KG9170-0000/side/55"
        },
        {
            "creation_method": "v4",
            "notes": [
                "UT22084-044-001-101"
            ],
            "flags": "",
            "folio": "F.28.b",
            "tibetan": "།ཆགས་པ་མེད་པས་དོན་རྣམས་འགྲུབ།",
            "english": "“Wealth is obtained through nonattachment.",
            "passage-xmlId": "UT22084-044-001-100",
            "creation_tool": "monlam-ai/84000",
            "volume": "44",
            "folio_xmlId": "UT4CZ5369-I1KG9170-0000/side/56"
        },
        {
            "creation_method": "v4",
            "notes": [],
            "flags": "",
            "folio": "F.28.b",
            "tibetan": "།སེར་སྣ་མེད་པས་ལོངས་སྤྱོད་འཕེལ།",
            "english": "Possessions increase by being without stinginess.",
            "passage-xmlId": "UT22084-044-001-100",
            "creation_tool": "monlam-ai/84000",
            "volume": "44",
            "folio_xmlId": "UT4CZ5369-I1KG9170-0000/side/56"
        },
        {
            "creation_method": "v4",
            "notes": [
                "UT22084-044-001-102"
            ],
            "flags": "",
            "folio": "F.28.b",
            "tibetan": "།གང་དང་གང་དུ་སྐྱེ་བ་དེར། །ཕྲག་དོག་མེད་པས་དབང་ཆེར་གྲགས།",
            "english": "One will be distinguished wherever one is born By being without jealousy.” {26}",
            "passage-xmlId": "UT22084-044-001-100",
            "creation_tool": "monlam-ai/84000",
            "volume": "44",
            "folio_xmlId": "UT4CZ5369-I1KG9170-0000/side/56"
        },
        {
            "creation_method": "v4",
            "notes": [],
            "flags": "",
            "folio": "F.28.b",
            "tibetan": "།ཇི་ལྟར་ལྷ་ཡི་མིག་འཐོབ་འགྱུར།",
            "english": "“How does one obtain divine sight?",
            "passage-xmlId": "UT22084-044-001-103",
            "creation_tool": "monlam-ai/84000",
            "volume": "44",
            "folio_xmlId": "UT4CZ5369-I1KG9170-0000/side/56"
        },
        {
            "creation_method": "v4",
            "notes": [
                "UT22084-044-001-104"
            ],
            "flags": "",
            "folio": "F.28.b",
            "tibetan": "།ལྷ་ཡི་རྣ་བ་ཇི་ལྟར་འཐོབ། །སེམས་ཅན་འཆི་འཕོ་སྐྱེ་བ་དག །འདྲེན་པ་གང་གིས་འཚལ་བར་འགྱུར།",
            "english": "How does one obtain divine hearing? And how, O Guide, does one know The dying, transmigration, and rebirth of beings?” {27}",
            "passage-xmlId": "UT22084-044-001-103",
            "creation_tool": "monlam-ai/84000",
            "volume": "44",
            "folio_xmlId": "UT4CZ5369-I1KG9170-0000/side/56"
        },
        {
            "creation_method": "v4",
            "notes": [],
            "flags": "",
            "folio": "F.28.b",
            "tibetan": "།མར་མེ་བྱིན་པས་མིག་འཐོབ་འགྱུར།",
            "english": "“Divine sight is obtained by giving lamps.",
            "passage-xmlId": "UT22084-044-001-105",
            "creation_tool": "monlam-ai/84000",
            "volume": "44",
            "folio_xmlId": "UT4CZ5369-I1KG9170-0000/side/56"
        },
        {
            "creation_method": "v4",
            "notes": [
                "UT22084-044-001-106",
                "UT22084-044-001-107"
            ],
            "flags": "",
            "folio": "F.28.b",
            "tibetan": "།རོལ་མོའི་སྒྲ་ཡིས་རྣ་བ་འདག །འཆི་འཕོ་སྐྱེ་ཤེས་ཡེ་ཤེས་ཀྱིས།",
            "english": "The ear is purified by giving music. The dying, transmigration, and rebirth of beings are known through wisdom.",
            "passage-xmlId": "UT22084-044-001-105",
            "creation_tool": "monlam-ai/84000",
            "volume": "44",
            "folio_xmlId": "UT4CZ5369-I1KG9170-0000/side/56"
        },
        {
            "creation_method": "v4",
            "notes": [],
            "flags": "",
            "folio": "F.28.b",
            "tibetan": "།དེ་དག་དེ་ལྟར་འགྲུབ་པར་འགྱུར།",
            "english": "Thus do these accomplishments arise.” {28}",
            "passage-xmlId": "UT22084-044-001-105",
            "creation_tool": "monlam-ai/84000",
            "volume": "44",
            "folio_xmlId": "UT4CZ5369-I1KG9170-0000/side/56"
        },
        {
            "creation_method": "v4",
            "notes": [
                "UT22084-044-001-109"
            ],
            "flags": "",
            "folio": "F.28.b",
            "tibetan": "།འདྲེན་པ་བྱང་ཆུབ་སེམས་དཔའ་ཡི། །ཟག་པ་གང་གིས་བས་པར་འགྱུར།",
            "english": "“O Guide, how do the defilements of bodhisattvas Come to be exhausted?",
            "passage-xmlId": "UT22084-044-001-108",
            "creation_tool": "monlam-ai/84000",
            "volume": "44",
            "folio_xmlId": "UT4CZ5369-I1KG9170-0000/side/56"
        },
        {
            "creation_method": "v4",
            "notes": [],
            "flags": "",
            "folio": "F.28.b",
            "tibetan": "།ཚེ་རབས་སྔ་དྲན་ཅིས་འགྱུར་ལགས།",
            "english": "How do they recollect previous lives?",
            "passage-xmlId": "UT22084-044-001-108",
            "creation_tool": "monlam-ai/84000",
            "volume": "44",
            "folio_xmlId": "UT4CZ5369-I1KG9170-0000/side/56"
        },
        {
            "creation_method": "v4",
            "notes": [
                "UT22084-044-001-110"
            ],
            "flags": "",
            "folio": "F.28.b",
            "tibetan": "།རྫུ་འཕྲུལ་ཅི་ཡིས་འཐོབ་པར་འགྱུར།",
            "english": "How do they obtain miraculous powers?” {29}",
            "passage-xmlId": "UT22084-044-001-108",
            "creation_tool": "monlam-ai/84000",
            "volume": "44",
            "folio_xmlId": "UT4CZ5369-I1KG9170-0000/side/56"
        },
        {
            "creation_method": "v4",
            "notes": [],
            "flags": "",
            "folio": "F.28.b",
            "tibetan": "།བཞོན་པ་བྱིན་པས་རྫུ་འཕྲུལ་འཐོབ།",
            "english": "“The miraculous powers are obtained by offering vehicles.",
            "passage-xmlId": "UT22084-044-001-111",
            "creation_tool": "monlam-ai/84000",
            "volume": "44",
            "folio_xmlId": "UT4CZ5369-I1KG9170-0000/side/56"
        },
        {
            "creation_method": "v4",
            "notes": [
                "UT22084-044-001-112"
            ],
            "flags": "",
            "folio": "F.28.b",
            "tibetan": "།དྲན་པ་བསྒོམས་པས་རྗེས་སུ་དྲན། །མཐའ་གཉིས་རབ་ཏུ་སྤང་བྱས་ན། །ཟག་པ་ཟད་པར་རེག་པར་འགྱུར།",
            "english": "The recollections are gained by cultivating mindfulness. They reach the cessation of defilements By fully abandoning the two extremes.” {30}",
            "passage-xmlId": "UT22084-044-001-111",
            "creation_tool": "monlam-ai/84000",
            "volume": "44",
            "folio_xmlId": "UT4CZ5369-I1KG9170-0000/side/56"
        },
        {
            "creation_method": "v4",
            "notes": [],
            "flags": "",
            "folio": "F.28.b",
            "tibetan": "།གང་གིས་ཞིང་ནི་ཕུན་སུམ་ཚོགས།",
            "english": "“How is the buddhafield perfected?",
            "passage-xmlId": "UT22084-044-001-113",
            "creation_tool": "monlam-ai/84000",
            "volume": "44",
            "folio_xmlId": "UT4CZ5369-I1KG9170-0000/side/56"
        },
        {
            "creation_method": "v4",
            "notes": [],
            "flags": "",
            "folio": "F.28.b",
            "tibetan": "།ཅིས་ནི་དགེ་འདུན་ཕུན་སུམ་ཚོགས།",
            "english": "How is its saṅgha perfected?",
            "passage-xmlId": "UT22084-044-001-113",
            "creation_tool": "monlam-ai/84000",
            "volume": "44",
            "folio_xmlId": "UT4CZ5369-I1KG9170-0000/side/56"
        },
        {
            "creation_method": "v4",
            "notes": [],
            "flags": "",
            "folio": "F.28.b",
            "tibetan": "།གང་གིས་ཕུན་སུམ་ཚོགས་འོད་འགྱུར།",
            "english": "How does its light shine perfectly",
            "passage-xmlId": "UT22084-044-001-113",
            "creation_tool": "monlam-ai/84000",
            "volume": "44",
            "folio_xmlId": "UT4CZ5369-I1KG9170-0000/side/56"
        },
        {
            "creation_method": "v4",
            "notes": [
                "UT22084-044-001-114",
                "UT22084-044-001-115"
            ],
            "flags": "",
            "folio": "F.28.b",
            "tibetan": "།གང་གིས་ཕྱོགས་བཅུར་ལྷང་ངེར་གདའ།",
            "english": "Such that the ten directions are illuminated?” {31}",
            "passage-xmlId": "UT22084-044-001-113",
            "creation_tool": "monlam-ai/84000",
            "volume": "44",
            "folio_xmlId": "UT4CZ5369-I1KG9170-0000/side/56"
        },
        {
            "creation_method": "v4",
            "notes": [],
            "flags": "",
            "folio": "F.28.b",
            "tibetan": "།སྨོན་ལམ་གྱིས་ནི་ཕུན་སུམ་ཞིང་།",
            "english": "“The buddhafield is perfected through aspiration.",
            "passage-xmlId": "UT22084-044-001-116",
            "creation_tool": "monlam-ai/84000",
            "volume": "44",
            "folio_xmlId": "UT4CZ5369-I1KG9170-0000/side/56"
        },
        {
            "creation_method": "v4",
            "notes": [
                "UT22084-044-001-117"
            ],
            "flags": "",
            "folio": "F.28.b",
            "tibetan": "།བསྡུ་བས་དགེ་འདུན་ཕུན་སུམ་ཚོགས། །འདིར་ནི་རིན་ཆེན་གདུགས་ཕུལ་བས། །ཕྱོགས་བཅུར་ལྷང་ངེར་སྣང་བར་འགྱུར། །",
            "english": "The saṅgha is perfected by magnetizing disciples. The ten directions are illuminated brightly By offering jeweled canopies.” {32}",
            "passage-xmlId": "UT22084-044-001-116",
            "creation_tool": "monlam-ai/84000",
            "volume": "44",
            "folio_xmlId": "UT4CZ5369-I1KG9170-0000/side/56"
        },
        {
            "creation_method": "v4",
            "notes": [
                "UT22084-044-001-119",
                "UT22084-044-001-120",
                "UT22084-044-001-121",
                "UT22084-044-001-122"
            ],
            "flags": "",
            "folio": "F.28.b",
            "tibetan": "ཆོས་རྣམས་ཐམས་ཅད་བསྡུ་བ་ནི། །ཆོས་གང་གིས་ནི་ཐོབ་པར་འགྱུར། །གང་དང་གང་དུ་སྐྱེས་པ་དེར། །བྱང་ཆུབ་སེམས་དཔའ་དགའ་བ་འཐོབ། །",
            "english": "“By what quality does one attain The embodiment of all qualities, So that a bodhisattva will be dear to beings Wherever they are born?” {33}",
            "passage-xmlId": "UT22084-044-001-118",
            "creation_tool": "monlam-ai/84000",
            "volume": "44",
            "folio_xmlId": "UT4CZ5369-I1KG9170-0000/side/56"
        },
        {
            "creation_method": "v4",
            "notes": [
                "UT22084-044-001-124"
            ],
            "flags": "",
            "folio": "F.28.b",
            "tibetan": "སེམས་ཅན་ཐམས་ཅད་ཐར་བྱའི་ཕྱིར། །བྱང་ཆུབ་དོན་དུ་སེམས་བཏུད་པ།",
            "english": "“By surrendering the mind to the purpose of awakening In order to liberate all beings,",
            "passage-xmlId": "UT22084-044-001-123",
            "creation_tool": "monlam-ai/84000",
            "volume": "44",
            "folio_xmlId": "UT4CZ5369-I1KG9170-0000/side/56"
        },
        {
            "creation_method": "v4",
            "notes": [],
            "flags": "",
            "folio": "F.28.b",
            "tibetan": "།དེས་ནི་ཆོས་རྣམས་བསྡུ་བ་འཐོབ། །དེར་ནི་དགའ་བའང་འཐོབ་པར་འགྱུར།",
            "english": "They attain the embodiment of all qualities And will thus be held dear.” {34}",
            "passage-xmlId": "UT22084-044-001-123",
            "creation_tool": "monlam-ai/84000",
            "volume": "44",
            "folio_xmlId": "UT4CZ5369-I1KG9170-0000/side/56"
        },
        {
            "creation_method": "v4",
            "notes": [
                "UT22084-044-001-126"
            ],
            "flags": "",
            "folio": "F.28.b",
            "tibetan": "།བསླབ་པ་ཅི་འདྲ་བསླབས་པ་དང་། །སེམས་ནི་ཅི་འདྲ་བསྒོམས་པ་ཡིས། །ཐུབ་པ་ཆེན་པོ་ཁྱོད་འདྲ་བའི། །སྟོན་པ་ཐམས་ཅད་མཁྱེན་པར་འགྱུར།",
            "english": "“In what instruction should one train, And how should one cultivate the mind, To become an omniscient teacher Like you, Great Sage?” {35}",
            "passage-xmlId": "UT22084-044-001-125",
            "creation_tool": "monlam-ai/84000",
            "volume": "44",
            "folio_xmlId": "UT4CZ5369-I1KG9170-0000/side/56"
        },
        {
            "creation_method": "v4",
            "notes": [],
            "flags": "",
            "folio": "F.28.b",
            "tibetan": "།སེམས་ཅན་མ་ལུས་ཐམས་ཅད་ལ། །མཉམ་པའི་སེམས་ཉིད་བསླབས་པ་དང་། །མཉམ་པར་སེམས་ནི་བསྒོམས་པས་ན། །ཐམས་ཅད་ཟིལ་གནོན་རྒྱལ་བར་འགྱུར།",
            "english": "“If one trains in being impartial To all beings without exception, And if the mind is cultivated in that impartiality, One will become an all-surpassing victorious one.” {36}",
            "passage-xmlId": "UT22084-044-001-127",
            "creation_tool": "monlam-ai/84000",
            "volume": "44",
            "folio_xmlId": "UT4CZ5369-I1KG9170-0000/side/56"
        },
        {
            "creation_method": "v4",
            "notes": [
                "UT22084-044-001-129",
                "UT22084-044-001-130"
            ],
            "flags": "",
            "folio": "F.28.b",
            "tibetan": "།སྐྱེ་བ་ཀུན་ཏུ་བྱང་ཆུབ་སེམས། །རྨི་ལམ་ན་ཡང་སེམས་དེ་ནི། །འདོར་མི་འགྱུར་ན་མ་ཉལ་ཚེ། །སྨོས་ཅི་འཚལ་བར་གང་གིས་འགྱུར།",
            "english": "“Throughout all one’s lives, How will the mind of awakening Never be abandoned even in a dream, Let alone while awake?” {37}",
            "passage-xmlId": "UT22084-044-001-128",
            "creation_tool": "monlam-ai/84000",
            "volume": "44",
            "folio_xmlId": "UT4CZ5369-I1KG9170-0000/side/56"
        },
        {
            "creation_method": "v4",
            "notes": [],
            "flags": "",
            "folio": "F.29.a",
            "tibetan": "།གྲོང་དང་གྲོང་ཁྱེར་རྣམས་སུའམ། །གང་དུ་གནས་པའི་ཡུལ་རྣམས་སུ།",
            "english": "“In whatever region one dwells, Whether a village or a city,",
            "passage-xmlId": "UT22084-044-001-131",
            "creation_tool": "monlam-ai/84000",
            "volume": "44",
            "folio_xmlId": "UT4CZ5369-I1KG9170-0000/side/57"
        },
        {
            "creation_method": "v4",
            "notes": [],
            "flags": "",
            "folio": "F.29.a",
            "tibetan": "།བྱང་ཆུབ་ལ་ནི་ཡང་དག་འཛུད།",
            "english": "By correctly guiding others toward awakening,",
            "passage-xmlId": "UT22084-044-001-131",
            "creation_tool": "monlam-ai/84000",
            "volume": "44",
            "folio_xmlId": "UT4CZ5369-I1KG9170-0000/side/57"
        },
        {
            "creation_method": "v4",
            "notes": [],
            "flags": "",
            "folio": "F.29.a",
            "tibetan": "།དེས་ན་སེམས་འདོར་མི་འགྱུར་རོ།",
            "english": "The mind of awakening is not abandoned.” {38}",
            "passage-xmlId": "UT22084-044-001-131",
            "creation_tool": "monlam-ai/84000",
            "volume": "44",
            "folio_xmlId": "UT4CZ5369-I1KG9170-0000/side/57"
        },
        {
            "creation_method": "v4",
            "notes": [
                "UT22084-044-001-133"
            ],
            "flags": "",
            "folio": "F.29.a",
            "tibetan": "།གང་དང་གང་དུ་སྐྱེ་བར་ཡང་།",
            "english": "“Wherever one is born,",
            "passage-xmlId": "UT22084-044-001-132",
            "creation_tool": "monlam-ai/84000",
            "volume": "44",
            "folio_xmlId": "UT4CZ5369-I1KG9170-0000/side/57"
        },
        {
            "creation_method": "v4",
            "notes": [],
            "flags": "",
            "folio": "F.29.a",
            "tibetan": "།ཇི་ལྟར་སྟོབས་ནི་ཆེ་འགྱུར་ཞིང་།",
            "english": "How can one acquire great strength",
            "passage-xmlId": "UT22084-044-001-132",
            "creation_tool": "monlam-ai/84000",
            "volume": "44",
            "folio_xmlId": "UT4CZ5369-I1KG9170-0000/side/57"
        },
        {
            "creation_method": "v4",
            "notes": [
                "UT22084-044-001-134"
            ],
            "flags": "",
            "folio": "F.29.a",
            "tibetan": "།རྟག་ཏུ་མཐུ་ཡིས་འཕགས་པ་དང་། །བདུད་རྣམས་བྱེ་བས་མི་ཚུགས་འགྱུར།",
            "english": "And always be elevated with power So that even ten million māras can do no harm?” {39}",
            "passage-xmlId": "UT22084-044-001-132",
            "creation_tool": "monlam-ai/84000",
            "volume": "44",
            "folio_xmlId": "UT4CZ5369-I1KG9170-0000/side/57"
        },
        {
            "creation_method": "v4",
            "notes": [
                "UT22084-044-001-136"
            ],
            "flags": "",
            "folio": "F.29.a",
            "tibetan": "།འདིར་ནི་སྙིང་པོ་ལྔ་བྱིན་ཞིང་།",
            "english": "“In this life, if one offers the five essences",
            "passage-xmlId": "UT22084-044-001-135",
            "creation_tool": "monlam-ai/84000",
            "volume": "44",
            "folio_xmlId": "UT4CZ5369-I1KG9170-0000/side/57"
        },
        {
            "creation_method": "v4",
            "notes": [],
            "flags": "",
            "folio": "F.29.a",
            "tibetan": "།སྐྲག་ལ་མི་འཇིགས་བྱིན་ན་ནི།",
            "english": "And gives courage to those who are afraid,",
            "passage-xmlId": "UT22084-044-001-135",
            "creation_tool": "monlam-ai/84000",
            "volume": "44",
            "folio_xmlId": "UT4CZ5369-I1KG9170-0000/side/57"
        },
        {
            "creation_method": "v4",
            "notes": [
                "UT22084-044-001-137"
            ],
            "flags": "",
            "folio": "F.29.a",
            "tibetan": "།གང་དང་གང་དུ་སྐྱེ་བར་ཡང་།",
            "english": "Then wherever one is born",
            "passage-xmlId": "UT22084-044-001-135",
            "creation_tool": "monlam-ai/84000",
            "volume": "44",
            "folio_xmlId": "UT4CZ5369-I1KG9170-0000/side/57"
        },
        {
            "creation_method": "v4",
            "notes": [],
            "flags": "",
            "folio": "F.29.a",
            "tibetan": "།དེས་ནི་སྟོབས་ནི་ཆེ་འགྱུར་ཏེ།",
            "english": "One will also have great strength,",
            "passage-xmlId": "UT22084-044-001-135",
            "creation_tool": "monlam-ai/84000",
            "volume": "44",
            "folio_xmlId": "UT4CZ5369-I1KG9170-0000/side/57"
        },
        {
            "creation_method": "v4",
            "notes": [
                "UT22084-044-001-138",
                "UT22084-044-001-139"
            ],
            "flags": "",
            "folio": "F.29.a",
            "tibetan": "།རྟག་ཏུ་མཐུ་ཡིས་འཕགས་པ་དང་། །བདུད་རྣམས་བྱེ་བས་མི་ཚུགས་སོ། །",
            "english": "Always be elevated with power, And be unharmed even by ten million māras.” {40}",
            "passage-xmlId": "UT22084-044-001-135",
            "creation_tool": "monlam-ai/84000",
            "volume": "44",
            "folio_xmlId": "UT4CZ5369-I1KG9170-0000/side/57"
        },
        {
            "creation_method": "v4",
            "notes": [
                "UT22084-044-001-141"
            ],
            "flags": "",
            "folio": "F.29.a",
            "tibetan": "བྱང་ཆུབ་སེམས་དཔའི་སྤྱོད་པ་དེ། །འཇིག་རྟེན་མགོན་གྱིས་མངོན་སུམ་དུ། །ལུང་བསྟན་པ་འདི་ཐོས་ནས་སུ།",
            "english": "Having heard this teaching On the conduct of bodhisattvas Directly from the Guardian of the World,",
            "passage-xmlId": "UT22084-044-001-140",
            "creation_tool": "monlam-ai/84000",
            "volume": "44",
            "folio_xmlId": "UT4CZ5369-I1KG9170-0000/side/57"
        },
        {
            "creation_method": "v4",
            "notes": [
                "UT22084-044-001-142",
                "UT22084-044-001-143",
                "UT22084-044-001-144"
            ],
            "flags": "",
            "folio": "F.29.a",
            "tibetan": "།སེང་གེ་ཡིད་ནི་དགའ་བར་འགྱུར།",
            "english": "Siṃha was overjoyed. {41}",
            "passage-xmlId": "UT22084-044-001-140",
            "creation_tool": "monlam-ai/84000",
            "volume": "44",
            "folio_xmlId": "UT4CZ5369-I1KG9170-0000/side/57"
        },
        {
            "creation_method": "v4",
            "notes": [],
            "flags": "",
            "folio": "F.29.a",
            "tibetan": "།སེང་གེ་གྲོགས་དང་ལྷན་ཅིག་ཏུ།",
            "english": "He and his companions",
            "passage-xmlId": "UT22084-044-001-145",
            "creation_tool": "monlam-ai/84000",
            "volume": "44",
            "folio_xmlId": "UT4CZ5369-I1KG9170-0000/side/57"
        },
        {
            "creation_method": "v4",
            "notes": [
                "UT22084-044-001-146",
                "UT22084-044-001-147"
            ],
            "flags": "",
            "folio": "F.29.a",
            "tibetan": "།འདི་སྐད་ཀྱི་ནི་ཚིག་སྨྲས་ཏེ། །སྤྱོད་པ་བསྟན་པ་འདི་ལ་ནི། །བདག་ཅག་རྗེས་སུ་བསླབ་པར་བགྱི།",
            "english": "Spoke the following words: “We will train In this teaching on conduct.” {42}",
            "passage-xmlId": "UT22084-044-001-145",
            "creation_tool": "monlam-ai/84000",
            "volume": "44",
            "folio_xmlId": "UT4CZ5369-I1KG9170-0000/side/57"
        },
        {
            "creation_method": "v4",
            "notes": [],
            "flags": "",
            "folio": "F.29.a",
            "tibetan": "།དེ་ནས་སངས་རྒྱས་འཛུམ་མཛད་དེ།",
            "english": "Then the Buddha smiled,",
            "passage-xmlId": "UT22084-044-001-148",
            "creation_tool": "monlam-ai/84000",
            "volume": "44",
            "folio_xmlId": "UT4CZ5369-I1KG9170-0000/side/57"
        },
        {
            "creation_method": "v4",
            "notes": [
                "UT22084-044-001-149"
            ],
            "flags": "",
            "folio": "F.29.a",
            "tibetan": "།སྟོང་གསུམ་པོ་ཡང་གཡོས་གྱུར་ནས།",
            "english": "And the trichiliocosm quaked.",
            "passage-xmlId": "UT22084-044-001-148",
            "creation_tool": "monlam-ai/84000",
            "volume": "44",
            "folio_xmlId": "UT4CZ5369-I1KG9170-0000/side/57"
        },
        {
            "creation_method": "v4",
            "notes": [
                "UT22084-044-001-150",
                "UT22084-044-001-151",
                "UT22084-044-001-152"
            ],
            "flags": "",
            "folio": "F.29.a",
            "tibetan": "།མ་ཕམ་པས་ནི་སངས་རྒྱས་ལ། །ཅི་ཞིག་སླད་དུ་འཛུམ་མཛད་པ། །ཐུབ་ཆེན་ལུང་བསྟན་གསོལ་ཞེས་ཞུས། །དེ་སྐད་ཞུ་བ་ཞུས་པ་དང་།",
            "english": "Ajita then asked the Buddha The following question: “Why did you smile? Great Sage, please explain this!” {43}",
            "passage-xmlId": "UT22084-044-001-148",
            "creation_tool": "monlam-ai/84000",
            "volume": "44",
            "folio_xmlId": "UT4CZ5369-I1KG9170-0000/side/57"
        },
        {
            "creation_method": "v4",
            "notes": [],
            "flags": "",
            "folio": "F.29.a",
            "tibetan": "།མ་ཕམ་པ་ལ་སངས་རྒྱས་ཀྱིས། །འདི་སྐད་ཅེས་ནི་བཀའ་སྩལ་ཏོ།",
            "english": "And so to Ajita The Buddha replied,",
            "passage-xmlId": "UT22084-044-001-153",
            "creation_tool": "monlam-ai/84000",
            "volume": "44",
            "folio_xmlId": "UT4CZ5369-I1KG9170-0000/side/57"
        },
        {
            "creation_method": "v4",
            "notes": [
                "UT22084-044-001-154"
            ],
            "flags": "",
            "folio": "F.29.a",
            "tibetan": "།གང་གི་ཕྱིར་ནི་འཛུམ་མཛད་པ། །མ་ཕམ་ང་ལས་འདིར་ཉོན་ཅིག །",
            "english": "“Ajita, please listen to the reason That I smiled. {44}",
            "passage-xmlId": "UT22084-044-001-153",
            "creation_tool": "monlam-ai/84000",
            "volume": "44",
            "folio_xmlId": "UT4CZ5369-I1KG9170-0000/side/57"
        },
        {
            "creation_method": "v4",
            "notes": [
                "UT22084-044-001-156",
                "UT22084-044-001-157",
                "UT22084-044-001-158"
            ],
            "flags": "",
            "folio": "F.29.a",
            "tibetan": "སངས་རྒྱས་བྱེ་བ་བརྒྱད་ཅུ་དང་། །གཞན་ཡང་ཁྲག་ཁྲིག་ཕྲག་བཅུ་ལ། །བྱང་ཆུབ་དོན་དུ་འདུས་ནས་ནི།",
            "english": "“Previously, these boys assembled before Eight hundred million buddhas and a quadrillion more. For the purpose of awakening,",
            "passage-xmlId": "UT22084-044-001-155",
            "creation_tool": "monlam-ai/84000",
            "volume": "44",
            "folio_xmlId": "UT4CZ5369-I1KG9170-0000/side/57"
        },
        {
            "creation_method": "v4",
            "notes": [
                "UT22084-044-001-159"
            ],
            "flags": "",
            "folio": "F.29.a",
            "tibetan": "།མི་ཡི་འདྲེན་པ་རྣམས་ལ་མཆོད། །",
            "english": "They made offerings to those guides of humans. {45}",
            "passage-xmlId": "UT22084-044-001-155",
            "creation_tool": "monlam-ai/84000",
            "volume": "44",
            "folio_xmlId": "UT4CZ5369-I1KG9170-0000/side/57"
        },
        {
            "creation_method": "v4",
            "notes": [
                "UT22084-044-001-161",
                "UT22084-044-001-162",
                "UT22084-044-001-163"
            ],
            "flags": "",
            "folio": "F.29.a",
            "tibetan": "རྫོགས་པའི་སངས་རྒྱས་རྐང་གཉིས་མཆོག །མར་མེ་མཛད་པ་ཚུན་ཆད་དུ།",
            "english": "“Since the time of Dīpaṅkara—The perfect buddha, supreme among people—",
            "passage-xmlId": "UT22084-044-001-160",
            "creation_tool": "monlam-ai/84000",
            "volume": "44",
            "folio_xmlId": "UT4CZ5369-I1KG9170-0000/side/57"
        },
        {
            "creation_method": "v4",
            "notes": [
                "UT22084-044-001-164"
            ],
            "flags": "",
            "folio": "F.29.a",
            "tibetan": "།བྲམ་ཟེའི་ཁྱེའུ་འདི་དག་རྣམས། །ང་ཡིས་ཡོངས་སུ་སྨིན་པར་བྱས།",
            "english": "I have been ripening These brahmin boys. {46}",
            "passage-xmlId": "UT22084-044-001-160",
            "creation_tool": "monlam-ai/84000",
            "volume": "44",
            "folio_xmlId": "UT4CZ5369-I1KG9170-0000/side/57"
        },
        {
            "creation_method": "v4",
            "notes": [
                "UT22084-044-001-166",
                "UT22084-044-001-167"
            ],
            "flags": "",
            "folio": "F.29.a",
            "tibetan": "།སྣང་བ་ཆེ་ཞེས་བྱ་བ་ཡི། །བསྐལ་པ་མཛེས་པ་འབྱུང་འགྱུར་ཏེ།",
            "english": "“When the splendid eon called Great Illumination arises,",
            "passage-xmlId": "UT22084-044-001-165",
            "creation_tool": "monlam-ai/84000",
            "volume": "44",
            "folio_xmlId": "UT4CZ5369-I1KG9170-0000/side/57"
        },
        {
            "creation_method": "v4",
            "notes": [],
            "flags": "",
            "folio": "F.29.a",
            "tibetan": "།དེ་དག་བསྐལ་པ་གཅིག་དེ་ལ།",
            "english": "In that single eon",
            "passage-xmlId": "UT22084-044-001-165",
            "creation_tool": "monlam-ai/84000",
            "volume": "44",
            "folio_xmlId": "UT4CZ5369-I1KG9170-0000/side/57"
        },
        {
            "creation_method": "v4",
            "notes": [
                "UT22084-044-001-168",
                "UT22084-044-001-169",
                "UT22084-044-001-171"
            ],
            "flags": "",
            "folio": "F.29.a",
            "tibetan": "།རྣམ་པར་འདྲེན་པར་འགྱུར་བ་སྟེ། །ཡེ་ཤེས་ཏོག་གི་རྒྱལ་མཚན་ཞེས། །འཇིག་རྟེན་འདྲེན་པ་རྣམས་སུ་འགྱུར། །འོད་དཔག་མེད་ཀྱི་བཀོད་པ་ལྟར། །དེ་དག་གི་ཡང་དེ་འདྲར་འགྱུར།",
            "english": "They will all become guides. {47} “They will become guides for the world Named Jñānaketudhvaja, And their array will be Just like that of Amitābha. {48}",
            "passage-xmlId": "UT22084-044-001-170",
            "creation_tool": "monlam-ai/84000",
            "volume": "44",
            "folio_xmlId": "UT4CZ5369-I1KG9170-0000/side/57"
        },
        {
            "creation_method": "v4",
            "notes": [
                "UT22084-044-001-173"
            ],
            "flags": "",
            "folio": "F.29.a",
            "tibetan": "།བྱམས་པ་ནས་ནི་བཟུང་ནས་སུ། །བསྐལ་པ་སུམ་བརྒྱ་ཚང་བར་ནི། །དེ་ཡི་བར་དུ་དུས་ཀུན་ཏུ། །རྟག་ཏུ་སངས་རྒྱས་ཕྲད་པར་འགྱུར། །",
            "english": "“From the time of Maitreya Through three hundred full eons, They will always Meet with buddhas. {49}",
            "passage-xmlId": "UT22084-044-001-172",
            "creation_tool": "monlam-ai/84000",
            "volume": "44",
            "folio_xmlId": "UT4CZ5369-I1KG9170-0000/side/57"
        },
        {
            "creation_method": "v4",
            "notes": [],
            "flags": "",
            "folio": "F.29.b",
            "tibetan": "འདི་དག་བྱང་ཆུབ་ཐོབ་པ་ཡི། །མིང་ནི་གང་སུས་ཐོས་པ་རྣམས།",
            "english": "“Moreover, whoever hears but the name Under which they attain awakening",
            "passage-xmlId": "UT22084-044-001-174",
            "creation_tool": "monlam-ai/84000",
            "volume": "44",
            "folio_xmlId": "UT4CZ5369-I1KG9170-0000/side/58"
        },
        {
            "creation_method": "v4",
            "notes": [
                "UT22084-044-001-175"
            ],
            "flags": "",
            "folio": "F.29.b",
            "tibetan": "།དེ་དག་ཐམས་ཅད་འཇིག་རྟེན་དུ། །ཀུན་མཁྱེན་གང་ཟག་མཚུངས་མེད་འགྱུར།",
            "english": "Shall, without exception, become incomparable And omniscient beings in the world. {50}",
            "passage-xmlId": "UT22084-044-001-174",
            "creation_tool": "monlam-ai/84000",
            "volume": "44",
            "folio_xmlId": "UT4CZ5369-I1KG9170-0000/side/58"
        },
        {
            "creation_method": "v4",
            "notes": [
                "UT22084-044-001-177"
            ],
            "flags": "",
            "folio": "F.29.b",
            "tibetan": "།གང་ཞིག་ལུང་བསྟན་འདི་ཐོས་ནས། །མོས་པ་སྐྱེད་པར་བྱེད་པ་ནི།",
            "english": "“Whoever, on hearing this prophecy, Becomes inspired",
            "passage-xmlId": "UT22084-044-001-176",
            "creation_tool": "monlam-ai/84000",
            "volume": "44",
            "folio_xmlId": "UT4CZ5369-I1KG9170-0000/side/58"
        },
        {
            "creation_method": "v4",
            "notes": [],
            "flags": "",
            "folio": "F.29.b",
            "tibetan": "།འཇིག་རྟེན་གསུམ་པོ་འདི་དག་ན། །དེ་དང་མཚུངས་པའི་བསོད་ནམས་མེད།",
            "english": "Will have merit unparalleled Throughout these three worlds. {51}",
            "passage-xmlId": "UT22084-044-001-176",
            "creation_tool": "monlam-ai/84000",
            "volume": "44",
            "folio_xmlId": "UT4CZ5369-I1KG9170-0000/side/58"
        },
        {
            "creation_method": "v4",
            "notes": [],
            "flags": "",
            "folio": "F.29.b",
            "tibetan": "།གང་གིས་བསྐལ་པ་དྲུག་སྟོང་དུ།",
            "english": "“Consider someone who for six thousand eons",
            "passage-xmlId": "UT22084-044-001-178",
            "creation_tool": "monlam-ai/84000",
            "volume": "44",
            "folio_xmlId": "UT4CZ5369-I1KG9170-0000/side/58"
        },
        {
            "creation_method": "v4",
            "notes": [
                "UT22084-044-001-179",
                "UT22084-044-001-180"
            ],
            "flags": "",
            "folio": "F.29.b",
            "tibetan": "།སངས་རྒྱས་ཞིང་རྣམས་ཐམས་ཅད་དུ། །རིན་ཆེན་རྣམས་ཀྱིས་བཀང་བྱས་ནས། །བྱང་ཆུབ་ཕྱིར་འདིར་བྱིན་པ་བས།",
            "english": "Filled up all the buddhafields With jewels and offered them For the purpose of awakening. {52}",
            "passage-xmlId": "UT22084-044-001-178",
            "creation_tool": "monlam-ai/84000",
            "volume": "44",
            "folio_xmlId": "UT4CZ5369-I1KG9170-0000/side/58"
        },
        {
            "creation_method": "v4",
            "notes": [
                "UT22084-044-001-182",
                "UT22084-044-001-183"
            ],
            "flags": "",
            "folio": "F.29.b",
            "tibetan": "།གང་གིས་ཆོས་ཀྱི་རྣམ་གྲངས་འདི། །ཐོས་ནས་བྱང་ཆུབ་ཕྱིར་འཇུག་ན། །སྔར་སྨོས་པ་ཡི་བསོད་ནམས་ཀྱིས། །གྲངས་དང་ཆར་ཡང་མི་ཕོད་དོ། །",
            "english": "“The tally of that person’s merit Could never match or compare to Hearing this Dharma presentation And setting out for the sake of awakening.” {53}",
            "passage-xmlId": "UT22084-044-001-181",
            "creation_tool": "monlam-ai/84000",
            "volume": "44",
            "folio_xmlId": "UT4CZ5369-I1KG9170-0000/side/58"
        },
        {
            "creation_method": "v4",
            "notes": [],
            "flags": "",
            "folio": "F.29.b",
            "tibetan": "ཆོས་འདི་བཤད་པའི་ཚེ་ན་ནི།",
            "english": "When this Dharma had been expounded,",
            "passage-xmlId": "UT22084-044-001-184",
            "creation_tool": "monlam-ai/84000",
            "volume": "44",
            "folio_xmlId": "UT4CZ5369-I1KG9170-0000/side/58"
        },
        {
            "creation_method": "v4",
            "notes": [
                "UT22084-044-001-185"
            ],
            "flags": "",
            "folio": "F.29.b",
            "tibetan": "།འཇིག་རྟེན་མགོན་པོའི་མཐུ་ཡིས་ནི།",
            "english": "By the power of the Protector of the World,",
            "passage-xmlId": "UT22084-044-001-184",
            "creation_tool": "monlam-ai/84000",
            "volume": "44",
            "folio_xmlId": "UT4CZ5369-I1KG9170-0000/side/58"
        },
        {
            "creation_method": "v4",
            "notes": [],
            "flags": "",
            "folio": "F.29.b",
            "tibetan": "།ལྷ་རྣམས་མེ་ཏོག་ཆར་པ་འབེབས།",
            "english": "The gods brought down a rain of flowers,",
            "passage-xmlId": "UT22084-044-001-184",
            "creation_tool": "monlam-ai/84000",
            "volume": "44",
            "folio_xmlId": "UT4CZ5369-I1KG9170-0000/side/58"
        },
        {
            "creation_method": "v4",
            "notes": [],
            "flags": "",
            "folio": "F.29.b",
            "tibetan": "།སྟོང་གསུམ་པོ་ཡང་གཡོས་པར་གྱུར།",
            "english": "And the trichiliocosm quaked. {54}",
            "passage-xmlId": "UT22084-044-001-184",
            "creation_tool": "monlam-ai/84000",
            "volume": "44",
            "folio_xmlId": "UT4CZ5369-I1KG9170-0000/side/58"
        },
        {
            "creation_method": "v4",
            "notes": [
                "UT22084-044-001-187"
            ],
            "flags": "",
            "folio": "F.29.b",
            "tibetan": "།སེང་གེ་གྲོགས་དང་བཅས་པ་ཡིས།",
            "english": "Siṃha, along with his companions,",
            "passage-xmlId": "UT22084-044-001-186",
            "creation_tool": "monlam-ai/84000",
            "volume": "44",
            "folio_xmlId": "UT4CZ5369-I1KG9170-0000/side/58"
        },
        {
            "creation_method": "v4",
            "notes": [],
            "flags": "",
            "folio": "F.29.b",
            "tibetan": "།མངོན་པར་ཤེས་པ་ལྔ་ཐོབ་ནས།",
            "english": "Obtained the five superknowledges and,",
            "passage-xmlId": "UT22084-044-001-186",
            "creation_tool": "monlam-ai/84000",
            "volume": "44",
            "folio_xmlId": "UT4CZ5369-I1KG9170-0000/side/58"
        },
        {
            "creation_method": "v4",
            "notes": [],
            "flags": "",
            "folio": "F.29.b",
            "tibetan": "།ཉིན་བདུན་བར་དུ་མཆོད་བྱས་ནས།",
            "english": "Having made offerings for one week,",
            "passage-xmlId": "UT22084-044-001-186",
            "creation_tool": "monlam-ai/84000",
            "volume": "44",
            "folio_xmlId": "UT4CZ5369-I1KG9170-0000/side/58"
        },
        {
            "creation_method": "v4",
            "notes": [
                "UT22084-044-001-188"
            ],
            "flags": "",
            "folio": "F.29.b",
            "tibetan": "།བསྟན་པ་ལ་ནི་རབ་ཏུ་བྱུང་།",
            "english": "Took ordination in the teaching. {55}",
            "passage-xmlId": "UT22084-044-001-186",
            "creation_tool": "monlam-ai/84000",
            "volume": "44",
            "folio_xmlId": "UT4CZ5369-I1KG9170-0000/side/58"
        },
        {
            "creation_method": "v4",
            "notes": [],
            "flags": "",
            "folio": "F.29.b",
            "tibetan": "།དེ་དག་ཀུན་གྱིས་ཏིང་འཛིན་འཐོབ།",
            "english": "All of them obtained absorption",
            "passage-xmlId": "UT22084-044-001-189",
            "creation_tool": "monlam-ai/84000",
            "volume": "44",
            "folio_xmlId": "UT4CZ5369-I1KG9170-0000/side/58"
        },
        {
            "creation_method": "v4",
            "notes": [
                "UT22084-044-001-190"
            ],
            "flags": "",
            "folio": "F.29.b",
            "tibetan": "།ཟད་མི་ཤེས་པའི་གཟུངས་ཀྱང་ཐོབ།",
            "english": "And inexhaustible retention.",
            "passage-xmlId": "UT22084-044-001-189",
            "creation_tool": "monlam-ai/84000",
            "volume": "44",
            "folio_xmlId": "UT4CZ5369-I1KG9170-0000/side/58"
        },
        {
            "creation_method": "v4",
            "notes": [
                "UT22084-044-001-191"
            ],
            "flags": "",
            "folio": "F.29.b",
            "tibetan": "།སེམས་ཅན་རྣམས་ཀྱི་དོན་བྱེད་དེ།",
            "english": "Wishing to accomplish the welfare of beings,",
            "passage-xmlId": "UT22084-044-001-189",
            "creation_tool": "monlam-ai/84000",
            "volume": "44",
            "folio_xmlId": "UT4CZ5369-I1KG9170-0000/side/58"
        },
        {
            "creation_method": "v4",
            "notes": [
                "UT22084-044-001-192",
                "UT22084-044-001-193"
            ],
            "flags": "",
            "folio": "F.29.b",
            "tibetan": "།སངས་རྒྱས་ཆོས་ལ་འཛུད་པར་བྱེད།",
            "english": "They brought them to the Dharma of the buddhas. {56}",
            "passage-xmlId": "UT22084-044-001-189",
            "creation_tool": "monlam-ai/84000",
            "volume": "44",
            "folio_xmlId": "UT4CZ5369-I1KG9170-0000/side/58"
        },
        {
            "creation_method": "v4",
            "notes": [
                "UT22084-044-001-195",
                "UT22084-044-001-196"
            ],
            "flags": "",
            "folio": "F.29.b",
            "tibetan": "།ཆོས་ཀྱི་རྣམ་གྲངས་འདི་བསྟན་པ་ན་སེམས་ཅན་བྱེ་བ་ཕྲག་བརྒྱད་ཅུ་བྱང་ཆུབ་མཆོག་ལ་ཞུགས་སོ། །བཅོམ་ལྡན་འདས་ཀྱིས་དེ་སྐད་ཅེས་བཀའ་སྩལ་ནས། སེང་གེ་གྲོགས་དང་བཅས་པ་དང་། ལྷ་དང་། མི་དང་། ལྷ་མ་ཡིན་དང་། དྲི་ཟར་བཅས་པའི་འཇིག་རྟེན་ཡི་རངས་ཏེ། བཅོམ་ལྡན་འདས་ཀྱིས་གསུངས་པ་ལ་མངོན་པར་བསྟོད་དོ།། །།",
            "english": "When this Dharma presentation was taught, eight hundred million beings set out for supreme awakening. When the Blessed One had spoken, Siṃha, along with his companions and the world with its gods, humans, asuras, and gandharvas, rejoiced and praised the words of the Blessed One.",
            "passage-xmlId": "UT22084-044-001-194",
            "creation_tool": "monlam-ai/84000",
            "volume": "44",
            "folio_xmlId": "UT4CZ5369-I1KG9170-0000/side/58"
        },
        {
            "creation_method": "v4",
            "notes": [],
            "flags": "",
            "folio": "F.29.b",
            "tibetan": "འཕགས་པ་དཀོན་མཆོག་བརྩེགས་པ་ཆེན་པོའི་ཆོས་ཀྱི་རྣམ་གྲངས་ལེའུ་སྟོང་ཕྲག་བརྒྱ་པ་ལས། སེང་གེས་ཞུས་པའི་ལེའུ་ཞེས་བྱ་སྟེ་སུམ་ཅུ་རྩ་བདུན་པ་རྫོགས་སོ།། །།རྒྱ་གར་གྱི་མཁན་པོ་དཱ་ན་ཤཱི་ལ་དང་། མུ་ནི་བར་མ་དང་། ཞུ་ཆེན་གྱི་ལོཙྪ་བ་བན་དེ་ཡེ་ཤེས་སྡེས་བསྒྱུར་ཅིང་ཞུས་ཏེ་སྐད་གསར་བཅད་ཀྱིས་ཀྱང་བཅོས་ནས་གཏན་ལ་ཕབ་པ། །",
            "english": "This concludes the thirty-seventh chapter, “Siṃha’s Questions,” from the eleven hundred chapters of the Dharma presentation of The Noble Great Heap of Jewels. The Indian preceptors Dānaśīla and Munivarman and the chief editor-translator Bandé Yeshé Dé translated, edited, and finalized this according to the new lexical register.",
            "passage-xmlId": "UT22084-044-001-197",
            "creation_tool": "monlam-ai/84000",
            "volume": "44",
            "folio_xmlId": "UT4CZ5369-I1KG9170-0000/side/58"
        }
    ],
    "text-id": "UT22084-044-001"
}